fiscal_calendar_helper/__init__.py
fiscal_calendar_helper/fiscal_calendar.csv
fiscal_calendar_helper/fiscal_calendar.py
fiscal_calendar_helper/helper.py
fiscal_calendar_helper-1.2.3.dist-info/METADATA
fiscal_calendar_helper-1.2.3.dist-info/WHEEL
fiscal_calendar_helper-1.2.3.dist-info/licenses/LICENSE.md
fiscal_calendar_helper-1.2.3.dist-info/RECORD
