Metadata-Version: 2.3
Name: fiscal-calendar-helper
Version: 1.2.3
Summary: A fiscal helper for retail calendars
Project-URL: homepage, https://github.com/Growthsayer/fiscal-helper
Project-URL: bug_tracker, https://github.com/Growthsayer/fiscal-helper/issues
Author: Phillip Geltman
License: MIT License
License-File: LICENSE.md
Classifier: License :: OSI Approved :: MIT License
Classifier: Operating System :: OS Independent
Classifier: Programming Language :: Python :: 3
Requires-Python: >=3.7
Requires-Dist: pandas>=1.3.1
